eustatspy/__init__.py
eustatspy/catalogue.py
eustatspy/client.py
eustatspy/exceptions.py
eustatspy/models.py
eustatspy/statistics.py
eustatspy/utils.py
eustatspy-1.0.0.dist-info/licenses/LICENSE.md
eustatspy-1.0.0.dist-info/METADATA
eustatspy-1.0.0.dist-info/WHEEL
eustatspy-1.0.0.dist-info/top_level.txt
eustatspy-1.0.0.dist-info/RECORD
