Metadata-Version: 2.4
Name: eustatspy
Version: 1.0.0
Summary: A Python wrapper for Eurostat APIs
Author-email: Emanuel Raptis <emanuelraptis@gmail.com>
License: MIT License
Project-URL: Homepage, https://github.com/xemarap/eustatspy
Project-URL: Documentation, https://github.com/xemarap/eustatspy/blob/main/README.md
Project-URL: Repository, https://github.com/xemarap/eustatspy
Project-URL: Bug Tracker, https://github.com/xemarap/eustatspy/issues
Keywords: eurostat,statistics,api,data,economics
Classifier: Programming Language :: Python :: 3
Classifier: Programming Language :: Python :: 3.7
Classifier: Programming Language :: Python :: 3.8
Classifier: Programming Language :: Python :: 3.9
Classifier: Programming Language :: Python :: 3.10
Classifier: Programming Language :: Python :: 3.11
Classifier: Programming Language :: Python :: 3.12
Classifier: Programming Language :: Python :: 3.13
Classifier: Operating System :: OS Independent
Classifier: Development Status :: 4 - Beta
Classifier: Intended Audience :: Developers
Classifier: Intended Audience :: Science/Research
Classifier: Topic :: Software Development :: Libraries :: Python Modules
Requires-Python: >=3.7
License-File: LICENSE.md
Requires-Dist: requests>=2.25.0
Requires-Dist: pandas>=1.3.0
Provides-Extra: dev
Requires-Dist: pytest>=6.0.0; extra == "dev"
Dynamic: license-file
